metadata_driver_aws/__init__.py
metadata_driver_aws/config_parser.py
metadata_driver_aws/data_plugin.py
metadata_driver_aws/log.py
metadata_driver_aws/s3_client.py
nevermined_metadata_driver_aws-0.3.0.dist-info/LICENSE
nevermined_metadata_driver_aws-0.3.0.dist-info/METADATA
nevermined_metadata_driver_aws-0.3.0.dist-info/NOTICE
nevermined_metadata_driver_aws-0.3.0.dist-info/WHEEL
nevermined_metadata_driver_aws-0.3.0.dist-info/top_level.txt
nevermined_metadata_driver_aws-0.3.0.dist-info/RECORD
