Metadata-Version: 2.1
Name: nevermined-metadata-driver-aws
Version: 0.3.0
Summary: 💧 Metadata S3 Driver Implementation
Home-page: https://github.com/nevermined-io/metadata-driver-aws
Author: nevermined-io
Author-email: root@nevermined.io
License: Apache Software License 2.0
Keywords: nevermined-metadata-driver-aws
Platform: UNKNOWN
Classifier: Development Status :: 5 - Production/Stable
Classifier: Intended Audience :: Developers
Classifier: License :: OSI Approved :: Apache Software License
Classifier: Natural Language :: English
Classifier: Programming Language :: Python :: 3.7
Classifier: Programming Language :: Python :: 3.8
License-File: LICENSE
License-File: NOTICE
Requires-Dist: coloredlogs (>=15.0.1)
Requires-Dist: boto3 (>=1.18.15)
Requires-Dist: PyYAML (>=5.4.1)
Requires-Dist: nevermined-metadata-driver-interface (>=0.4.0)
Provides-Extra: dev
Requires-Dist: bumpversion ; extra == 'dev'
Requires-Dist: pkginfo ; extra == 'dev'
Requires-Dist: twine ; extra == 'dev'
Requires-Dist: watchdog ; extra == 'dev'
Requires-Dist: pytest (>=6.2.4) ; extra == 'dev'
Provides-Extra: test
Requires-Dist: pytest (>=6.2.4) ; extra == 'test'
